README.md
setup.py
Topsis_Manish_101903228/Topsis.py
Topsis_Manish_101903228.egg-info/PKG-INFO
Topsis_Manish_101903228.egg-info/SOURCES.txt
Topsis_Manish_101903228.egg-info/dependency_links.txt
Topsis_Manish_101903228.egg-info/entry_points.txt
Topsis_Manish_101903228.egg-info/requires.txt
Topsis_Manish_101903228.egg-info/top_level.txt