Metadata-Version: 2.1
Name: Topsis-Manish-101903228
Version: 0.0.2
Summary: A package Calculates Topsis Score and Rank them accordingly, for example selection of best project
Home-page: UNKNOWN
Author: Manish Sharma
Author-email: manish1206s@gmail.com
License: MIT
Platform: UNKNOWN
